tennet/__init__.py
tennet/netztransparenz.py
tennet/tennet.py
tennet/utils.py
tennet_py-0.2.2.dist-info/LICENSE.MD
tennet_py-0.2.2.dist-info/METADATA
tennet_py-0.2.2.dist-info/WHEEL
tennet_py-0.2.2.dist-info/top_level.txt
tennet_py-0.2.2.dist-info/RECORD
