Metadata-Version: 2.1
Name: tennet-py
Version: 0.2.2
Summary: A python API wrapper for TenneT System & transmission data
Home-page: https://github.com/fboerman/tennet-py
Author: Frank Boerman
Author-email: frank@fboerman.nl
License: MIT
Keywords: TenneT data api energy
Classifier: Development Status :: 5 - Production/Stable
Classifier: Intended Audience :: Developers
Classifier: Topic :: Scientific/Engineering
Classifier: License :: OSI Approved :: MIT License
Classifier: Programming Language :: Python :: 3.9
Classifier: Programming Language :: Python :: 3.10
Classifier: Programming Language :: Python :: 3.11
License-File: LICENSE.MD
Requires-Dist: requests
Requires-Dist: pandas
Requires-Dist: lxml
